biocommons/seqrepo/__init__.py
biocommons/seqrepo/_versionwarning.py
biocommons/seqrepo/cli.py
biocommons/seqrepo/config.py
biocommons/seqrepo/dataproxy.py
biocommons/seqrepo/seqrepo.py
biocommons/seqrepo/utils.py
biocommons/seqrepo/_internal/__init__.py
biocommons/seqrepo/_internal/logging_support.py
biocommons/seqrepo/_internal/translate.py
biocommons/seqrepo/fastadir/__init__.py
biocommons/seqrepo/fastadir/bases.py
biocommons/seqrepo/fastadir/fabgz.py
biocommons/seqrepo/fastadir/fastadir.py
biocommons/seqrepo/fastadir/_data/migrations/0000-base.py
biocommons/seqrepo/fastadir/_data/migrations/0001-initial.py
biocommons/seqrepo/fastaiter/__init__.py
biocommons/seqrepo/fastaiter/fastaiter.py
biocommons/seqrepo/seqaliasdb/__init__.py
biocommons/seqrepo/seqaliasdb/seqaliasdb.py
biocommons/seqrepo/seqaliasdb/_data/migrations/0000-base.py
biocommons/seqrepo/seqaliasdb/_data/migrations/0001-initial.py
biocommons.seqrepo-0.6.11.dist-info/LICENSE
biocommons.seqrepo-0.6.11.dist-info/METADATA
biocommons.seqrepo-0.6.11.dist-info/WHEEL
biocommons.seqrepo-0.6.11.dist-info/entry_points.txt
biocommons.seqrepo-0.6.11.dist-info/top_level.txt
biocommons.seqrepo-0.6.11.dist-info/RECORD
