Metadata-Version: 2.1
Name: biocommons.seqrepo
Version: 0.6.11
Summary: Non-redundant, compressed, journalled, file-based storage for biological sequences
Author-email: biocommons contributors <biocommons-dev@googlegroups.com>
Project-URL: Homepage, https://github.com/biocommons/biocommons.seqrepo
Project-URL: Bug Tracker, https://github.com/biocommons/biocommons.seqrepo/issues
Classifier: Programming Language :: Python :: 3
Classifier: Programming Language :: Python :: 3.10
Classifier: Programming Language :: Python :: 3.11
Classifier: Programming Language :: Python :: 3.12
Classifier: License :: OSI Approved :: Apache Software License
Classifier: Operating System :: OS Independent
Requires-Python: >=3.10
License-File: LICENSE
Requires-Dist: bioutils>0.4
Requires-Dist: coloredlogs~=15.0
Requires-Dist: ipython~=8.4
Requires-Dist: pysam~=0.22
Requires-Dist: requests~=2.31
Requires-Dist: tqdm~=4.66
Requires-Dist: typing-extensions
Requires-Dist: yoyo-migrations~=9.0
Provides-Extra: dev
Requires-Dist: bandit~=1.7; extra == "dev"
Requires-Dist: build~=0.8; extra == "dev"
Requires-Dist: flake8~=4.0; extra == "dev"
Requires-Dist: ipython~=8.4; extra == "dev"
Requires-Dist: isort~=5.10; extra == "dev"
Requires-Dist: mypy-extensions~=1.0; extra == "dev"
Requires-Dist: pre-commit~=3.4; extra == "dev"
Requires-Dist: pylint~=2.14; extra == "dev"
Requires-Dist: pyright~=1.1; extra == "dev"
Requires-Dist: requests-html~=0.10; extra == "dev"
Requires-Dist: ruff==0.4.4; extra == "dev"
Provides-Extra: docs
Requires-Dist: mkdocs; extra == "docs"
Provides-Extra: tests
Requires-Dist: tox~=3.25; extra == "tests"
Requires-Dist: pytest-cov~=4.1; extra == "tests"
Requires-Dist: pytest-optional-tests; extra == "tests"
Requires-Dist: pytest~=7.1; extra == "tests"
Requires-Dist: vcrpy; extra == "tests"
